plone.resource-3.0.3-py3.13-nspkg.pth
plone/resource/__init__.py
plone/resource/browser.zcml
plone/resource/caching.py
plone/resource/caching.zcml
plone/resource/configure.zcml
plone/resource/directory.py
plone/resource/download.py
plone/resource/events.py
plone/resource/file.py
plone/resource/file.zcml
plone/resource/interfaces.py
plone/resource/manifest.py
plone/resource/meta.zcml
plone/resource/permissions.zcml
plone/resource/profiles.zcml
plone/resource/testing.py
plone/resource/testing.zcml
plone/resource/traversal.py
plone/resource/utils.py
plone/resource/zcml.py
plone/resource/profiles/default/componentregistry.xml
plone/resource/profiles/default/metadata.xml
plone/resource/profiles/default/rolemap.xml
plone/resource/profiles/default/toolset.xml
plone/resource/tests/__init__.py
plone/resource/tests/resources.zip
plone/resource/tests/test_directory.py
plone/resource/tests/test_file.py
plone/resource/tests/test_integration.py
plone/resource/tests/test_manifest.py
plone/resource/tests/test_traversal.py
plone/resource/tests/test_utils.py
plone/resource/tests/test_zcml.py
plone/resource/tests/test_zip_download.py
plone/resource/tests/resources/demo/foo/test.html
plone/resource/tests/resources/demo/manifest-test/manifest.cfg
plone/resource/tests/resources/demo/manifest-test/test.txt
plone/resource/tests/zipfiles/manifest-name-override.zip
plone/resource/tests/zipfiles/multiple-top-level-dirs.zip
plone/resource/tests/zipfiles/no-manifest.zip
plone/resource/tests/zipfiles/no-top-level-dir.zip
plone/resource/tests/zipfiles/normal.zip
plone_resource-3.0.3.dist-info/METADATA
plone_resource-3.0.3.dist-info/WHEEL
plone_resource-3.0.3.dist-info/entry_points.txt
plone_resource-3.0.3.dist-info/namespace_packages.txt
plone_resource-3.0.3.dist-info/top_level.txt
plone_resource-3.0.3.dist-info/RECORD
