Metadata-Version: 2.4
Name: plone.resource
Version: 3.0.3
Summary: Static files for Plone
Home-page: https://pypi.org/project/plone.resource
Author: David Glick, Plone Foundation
Author-email: davidglick@groundwire.org
License: GPL version 2 or later
Keywords: plone resource
Classifier: Development Status :: 5 - Production/Stable
Classifier: Framework :: Plone
Classifier: Framework :: Plone :: 6.0
Classifier: Framework :: Plone :: Core
Classifier: Framework :: Zope :: 5
Classifier: License :: OSI Approved :: GNU General Public License v2 or later (GPLv2+)
Classifier: Programming Language :: Python
Classifier: Programming Language :: Python :: 3.8
Classifier: Programming Language :: Python :: 3.9
Classifier: Programming Language :: Python :: 3.10
Classifier: Programming Language :: Python :: 3.11
Requires-Python: >=3.8
Requires-Dist: plone.caching
Requires-Dist: python-dateutil
Requires-Dist: setuptools
Requires-Dist: z3c.caching
Requires-Dist: Zope
Requires-Dist: Products.BTreeFolder2
Requires-Dist: Products.CMFCore
Requires-Dist: Products.GenericSetup
Provides-Extra: test
Requires-Dist: plone.app.testing; extra == "test"
Requires-Dist: plone.testing; extra == "test"
Dynamic: author
Dynamic: author-email
Dynamic: classifier
Dynamic: description
Dynamic: description-content-type
Dynamic: home-page
Dynamic: keywords
Dynamic: license
Dynamic: provides-extra
Dynamic: requires-dist
Dynamic: requires-python
Dynamic: summary
